scoping_resolver/__init__.py
scoping_resolver-0.0.5.dist-info/METADATA
scoping_resolver-0.0.5.dist-info/RECORD
scoping_resolver-0.0.5.dist-info/WHEEL
scoping_resolver-0.0.5.dist-info/entry_points.txt
scoping_resolver-0.0.5.dist-info/top_level.txt
test/__init__.py
test/test_simple.py
