Metadata-Version: 2.1
Name: scoping-resolver
Version: 0.0.5
Summary: UNKNOWN
Home-page: https://github.com/thautwarm/symbol-resolver
Author: thautwarm
Author-email: twshere@outlook.com
License: mit
Platform: UNKNOWN
Classifier: Programming Language :: Python :: 3.6
Classifier: Programming Language :: Python :: 3.7
Classifier: Programming Language :: Python :: Implementation :: CPython
Requires-Python: >=3.6.0
